README.md
setup.py
pythonccf/__main__.py
pythonccf/find_declared.py
pythonccf/parse.py
pythonccf/process.py
pythonccf/pythonccf.py
pythonccf/types.py
pythonccf.egg-info/PKG-INFO
pythonccf.egg-info/SOURCES.txt
pythonccf.egg-info/dependency_links.txt
pythonccf.egg-info/entry_points.txt
pythonccf.egg-info/top_level.txt
test/test.py
test/test_asd_qwe.py