Metadata-Version: 2.1
Name: pythonccf
Version: 0.2.0
Summary: A simple tool for renaming and documenting Python code according to PEP
Home-page: https://github.com/nikitosoleil/metaprog/tree/lab/2-python/L2
Author: Mykyta Oliinyk
Author-email: nikiolei@gmail.com
License: UNKNOWN
Platform: UNKNOWN
